{

"GxObject":{"ObjectType":"BusinessComponent","Name":"Venta","idConnectivitySupport":"idInherit","Structure":{"Levels":[{"Name":"Venta","ParentLevel":"","LevelName":"Venta","Description":"Venta","Attributes":[{"Name":"VentaId","Caption":"Venta Id","default":"0","AutoNumber":"true","IsKey":"true","ReadOnly":"false","AttributeType":"int","Description":"Venta Id","Length":"4","Decimals":"0","Signed":"false","AllowDBNulls":"false","Domain":"Id","InternalName":"VentaId","InputPicture":"ZZZ9","Type":"xs:int"},{"Name":"VentaHoraFecha","Caption":"Venta Hora Fecha","default":"","IsKey":"false","ReadOnly":"false","AttributeType":"dtime","Description":"Venta Hora Fecha","Length":"8","Decimals":"5","Signed":"false","AllowDBNulls":"false","InternalName":"VentaHoraFecha","DescriptionAtt":"true","InputPicture":"99/99/99 99:99","Type":"xs:string"},{"Name":"SectorId","Caption":"Sector Id","default":"0","IsKey":"false","ReadOnly":"false","AttributeType":"int","Description":"Sector Id","Length":"4","Decimals":"0","Signed":"false","AllowDBNulls":"false","Domain":"Id","InternalName":"SectorId","InputPicture":"ZZZ9","Type":"xs:int"},{"Name":"EventoId","Caption":"Evento Id","default":"0","IsKey":"false","ReadOnly":"false","AttributeType":"int","Description":"Evento Id","Length":"4","Decimals":"0","Signed":"false","AllowDBNulls":"false","Domain":"Id","InternalName":"EventoId","InputPicture":"ZZZ9","Type":"xs:int"}]}]},"Relations":{"ManyToOne":{"references":[]}}}
}
